modson_default_modules/VERSION
modson_default_modules/android.py
modson_default_modules/java.py
modson_default_modules-0.1.0.dist-info/licenses/LICENSE
modson_default_modules-0.1.0.dist-info/METADATA
modson_default_modules-0.1.0.dist-info/WHEEL
modson_default_modules-0.1.0.dist-info/entry_points.txt
modson_default_modules-0.1.0.dist-info/top_level.txt
modson_default_modules-0.1.0.dist-info/RECORD
