Metadata-Version: 2.4
Name: modson-default-modules
Version: 0.1.0
Summary: Some usefull custom Meson modules compatible with modson.
Home-page: https://github.com/alex-bouget/modson-default-modules
Author: alex-bouget
Classifier: Development Status :: 4 - Beta
Classifier: Environment :: Console
Classifier: Intended Audience :: Developers
Classifier: License :: OSI Approved :: MIT License
Classifier: Programming Language :: Python :: 3 :: Only
Classifier: Topic :: Software Development :: Build Tools
License-File: LICENSE
Requires-Dist: meson>=1.0.0
Requires-Dist: modson>=1.0.0
Dynamic: author
Dynamic: classifier
Dynamic: description
Dynamic: description-content-type
Dynamic: home-page
Dynamic: license-file
Dynamic: requires-dist
Dynamic: summary
